{
  "errors": [],
  "warnings": [],
  "version": "4.46.0",
  "hash": "b8e0826a5bb586418fce",
  "publicPath": "/static/",
  "outputPath": "/home/sam/Desktop/Sites/kincare-frontity/build/static",
  "assetsByChunkName": {
    "kincare-frontity": [
      "kincare-frontity.module.js",
      "kincare-frontity.c0c442e822a3e767672b.hot-update.js"
    ]
  },
  "assets": [
    {
      "name": "c0c442e822a3e767672b.hot-update.json",
      "size": 58,
      "chunks": [],
      "chunkNames": [],
      "info": {
        "hotModuleReplacement": true,
        "immutable": true
      },
      "emitted": false
    },
    {
      "name": "images/dots-square.png",
      "size": 372,
      "chunks": [],
      "chunkNames": [],
      "info": {
        "sourceFilename": "packages/kincare-theme/src/img/dots-square.png"
      },
      "emitted": false
    },
    {
      "name": "images/home-care-alliance.png",
      "size": 15486,
      "chunks": [],
      "chunkNames": [],
      "info": {
        "sourceFilename": "packages/kincare-theme/src/img/home-care-alliance.png"
      },
      "emitted": false
    },
    {
      "name": "images/logo.png",
      "size": 12480,
      "chunks": [],
      "chunkNames": [],
      "info": {
        "sourceFilename": "packages/kincare-theme/src/img/logo.png"
      },
      "emitted": false
    },
    {
      "name": "kincare-frontity.c0c442e822a3e767672b.hot-update.js",
      "size": 26839,
      "chunks": [
        "kincare-frontity"
      ],
      "chunkNames": [
        "kincare-frontity"
      ],
      "info": {
        "hotModuleReplacement": true,
        "immutable": true
      },
      "emitted": false
    },
    {
      "name": "kincare-frontity.module.js",
      "size": 8606288,
      "chunks": [
        "kincare-frontity"
      ],
      "chunkNames": [
        "kincare-frontity"
      ],
      "info": {},
      "emitted": false
    }
  ],
  "filteredAssets": 0,
  "entrypoints": {
    "kincare-frontity": {
      "chunks": [
        "kincare-frontity"
      ],
      "assets": [
        "kincare-frontity.module.js",
        "kincare-frontity.c0c442e822a3e767672b.hot-update.js"
      ],
      "children": {},
      "childAssets": {}
    }
  },
  "namedChunkGroups": {
    "kincare-frontity": {
      "chunks": [
        "kincare-frontity"
      ],
      "assets": [
        "kincare-frontity.module.js",
        "kincare-frontity.c0c442e822a3e767672b.hot-update.js"
      ],
      "children": {},
      "childAssets": {}
    }
  },
  "chunks": [
    {
      "id": "kincare-frontity",
      "rendered": true,
      "initial": true,
      "entry": true,
      "size": 2351595,
      "names": [
        "kincare-frontity"
      ],
      "files": [
        "kincare-frontity.module.js",
        "kincare-frontity.c0c442e822a3e767672b.hot-update.js"
      ],
      "hash": "538179fde6d5dcd496da",
      "siblings": [],
      "parents": [],
      "children": [],
      "childrenByOrder": {},
      "modules": [],
      "filteredModules": 0,
      "origins": []
    }
  ],
  "logging": {
    "webpack.buildChunkGraph.visitModules": {
      "entries": [],
      "filteredEntries": 2,
      "debug": false
    }
  },
  "children": [],
  "generator": "loadable-components"
}